wakeword_detector/__init__.py
wakeword_detector/__main__.py
wakeword_detector/__version__.py
wakeword_detector/browse_audio.py
wakeword_detector/detector.py
wakeword_detector/dev_ui.py
wakeword_detector/export_onnx.py
wakeword_detector/extract_features.py
wakeword_detector/listen.py
wakeword_detector/record_audio.py
wakeword_detector/server.py
wakeword_detector/start.py
wakeword_detector/train.py
wakeword_detector-0.0.44.dist-info/licenses/LICENSE
wakeword_detector-0.0.44.dist-info/METADATA
wakeword_detector-0.0.44.dist-info/WHEEL
wakeword_detector-0.0.44.dist-info/entry_points.txt
wakeword_detector-0.0.44.dist-info/top_level.txt
wakeword_detector-0.0.44.dist-info/RECORD
